{
  "meta": {
    "created_date": "2024-08-06T17:20:11",
    "updated_date": "2024-10-15T21:50:43",
    "field_reference": "https://developer.wordpress.org/rest-api/reference/pages/",
    "api_version": "v2",
    "api_url": "https://api.cannabis.ca.gov/wp-json/wp/v2/",
    "object_url": "https://api.cannabis.ca.gov/wp-json/wp/v2/pages/19263",
    "process": {
      "source_code": "https://github.com/cagov/wordpress-to-github",
      "source_data": "https://api.cannabis.ca.gov",
      "deployment_target": "https://github.com/cagov/static-content-cannabis/tree/staging"
    },
    "refresh_frequency": "as needed"
  },
  "data": {
    "id": 19263,
    "date": "2024-08-06T10:20:11",
    "date_gmt": "2024-08-06T17:20:11",
    "guid": "https://api.cannabis.ca.gov/?page_id=19263",
    "modified": "2024-10-15T14:50:43",
    "modified_gmt": "2024-10-15T21:50:43",
    "slug": "business-people-and-owners",
    "status": "publish",
    "type": "page",
    "link": "https://api.cannabis.ca.gov/cultivation-licensing-system/cls-renewal-user-guide/business-people-and-owners/",
    "title": "Verifying business, people, and owners during CLS renewal",
    "excerpt": "<p>Ensuring accuracy of all owners and other people listed in the CLS portal during renewal is a critical step in the process. Review these steps to verify owners and financial interest holders.</p>\n",
    "author": 32,
    "featured_media": 0,
    "parent": 19257,
    "menu_order": 0,
    "comment_status": "closed",
    "ping_status": "closed",
    "template": "/code/wp-content/plugins/ca-design-system-gutenberg-blocks/includes/templates/template-page.php",
    "meta": {
      "_stopmodifiedupdate": false,
      "_modified_date": "",
      "footnotes": ""
    },
    "categories": [
      "All"
    ],
    "tags": [],
    "design_system_fields": {
      "template": "template-page"
    },
    "og_meta": {
      "editor": {
        "platform": "WordPress",
        "plugin": "autodescription",
        "plugin_name": "The SEO Framework",
        "plugin_version": "4.1.5.1",
        "editor_url": "https://api.cannabis.ca.gov"
      },
      "site_name": "Department of Cannabis Control",
      "site_description": "Learn about California cannabis laws and licenses",
      "site_url": "https://api.cannabis.ca.gov",
      "canonical_url": "https://api.cannabis.ca.gov/cultivation-licensing-system/cls-renewal-user-guide/business-people-and-owners/",
      "page_title": "Verifying business, people, and owners during CLS renewal",
      "page_description": "Learn about California cannabis laws and licenses",
      "page_social_image_url": "https://api.cannabis.ca.gov/wp-content/uploads/2021/07/cropped-Cannabis_horizontal_social.png",
      "page_social_image_width": 1200,
      "page_social_image_height": 630,
      "page_social_image_alt": "",
      "meta_title": "Verifying business, people, and owners during CLS renewal",
      "meta_description": "Learn about California cannabis laws and licenses",
      "meta_canonical_url": "https://api.cannabis.ca.gov/cultivation-licensing-system/cls-renewal-user-guide/business-people-and-owners/",
      "open_graph_title": "Verifying business, people, and owners during CLS renewal",
      "open_graph_description": "Learn about California cannabis laws and licenses",
      "twitter_title": "Verifying business, people, and owners during CLS renewal",
      "twitter_description": "Learn about California cannabis laws and licenses"
    },
    "headless_categories": [
      {
        "term_id": 1,
        "name": "All",
        "slug": "all",
        "term_group": 0,
        "term_taxonomy_id": 1,
        "taxonomy": "category",
        "description": "",
        "parent": 0,
        "filter": "raw",
        "cat_ID": 1,
        "category_description": "",
        "cat_name": "All",
        "category_nicename": "all",
        "category_parent": 0
      }
    ],
    "headless_tags": [],
    "headless_publishing": [],
    "headless_preview": [],
    "wordpress_url": "https://api.cannabis.ca.gov/cultivation-licensing-system/cls-renewal-user-guide/business-people-and-owners/"
  }
}