{
  "meta": {
    "created_date": "2023-01-24T16:53:53",
    "updated_date": "2023-01-31T23:22:06",
    "field_reference": "https://developer.wordpress.org/rest-api/reference/pages/",
    "api_version": "v2",
    "api_url": "https://api.cannabis.ca.gov/wp-json/wp/v2/",
    "object_url": "https://api.cannabis.ca.gov/wp-json/wp/v2/pages/12972",
    "process": {
      "source_code": "https://github.com/cagov/wordpress-to-github",
      "source_data": "https://api.cannabis.ca.gov",
      "deployment_target": "https://github.com/cagov/static-content-cannabis/tree/main"
    },
    "refresh_frequency": "as needed"
  },
  "data": {
    "id": 12972,
    "date": "2023-01-24T08:53:53",
    "date_gmt": "2023-01-24T16:53:53",
    "guid": "https://api.cannabis.ca.gov/?page_id=12972",
    "modified": "2023-01-31T15:22:06",
    "modified_gmt": "2023-01-31T23:22:06",
    "slug": "cultivation_draft",
    "status": "publish",
    "type": "page",
    "link": "https://api.cannabis.ca.gov/cultivation_draft/",
    "title": "[Draft] Cultivation",
    "excerpt": "<p>Cultivators grow all of the cannabis plants that are harvested, sold as flower, and made into products. Their operations look like other agricultural operations in California. Cannabis cultivation is a multi-step process that includes: Cultivation licenses If you want to grow cannabis and sell it in California, you will need a cultivation license. The type [&hellip;]</p>\n",
    "author": "Wes Breazell",
    "featured_media": 0,
    "parent": 0,
    "menu_order": 0,
    "comment_status": "closed",
    "ping_status": "closed",
    "template": "/code/wp-content/plugins/ca-design-system-gutenberg-blocks/includes/templates/template-page.php",
    "meta": {
      "_stopmodifiedupdate": false,
      "_modified_date": ""
    },
    "categories": [],
    "tags": [],
    "design_system_fields": {
      "template": "template-page"
    },
    "og_meta": {
      "editor": {
        "platform": "WordPress",
        "plugin": "autodescription",
        "plugin_name": "The SEO Framework",
        "plugin_version": "4.1.5.1",
        "editor_url": "https://api.cannabis.ca.gov"
      },
      "site_name": "Department of Cannabis Control",
      "site_description": "Learn about California cannabis laws and licenses",
      "site_url": "https://api.cannabis.ca.gov",
      "canonical_url": "https://api.cannabis.ca.gov/cultivation_draft/",
      "page_title": "[Draft] Cultivation",
      "page_description": "Learn about California cannabis laws and licenses",
      "page_social_image_url": "https://api.cannabis.ca.gov/wp-content/uploads/2021/07/cropped-Cannabis_horizontal_social.png",
      "page_social_image_width": 1200,
      "page_social_image_height": 630,
      "page_social_image_alt": "",
      "meta_title": "[Draft] Cultivation",
      "meta_description": "Learn about California cannabis laws and licenses",
      "meta_canonical_url": "https://api.cannabis.ca.gov/cultivation_draft/",
      "open_graph_title": "[Draft] Cultivation",
      "open_graph_description": "Learn about California cannabis laws and licenses",
      "twitter_title": "[Draft] Cultivation",
      "twitter_description": "Learn about California cannabis laws and licenses"
    },
    "headless_categories": [],
    "headless_tags": [],
    "headless_publishing": [],
    "headless_preview": [],
    "wordpress_url": "https://api.cannabis.ca.gov/cultivation_draft/"
  }
}