{
  "meta": {
    "created_date": "2022-01-26T16:55:22",
    "updated_date": "2025-10-14T22:09:31",
    "field_reference": "https://developer.wordpress.org/rest-api/reference/pages/",
    "api_version": "v2",
    "api_url": "https://api.cannabis.ca.gov/wp-json/wp/v2/",
    "object_url": "https://api.cannabis.ca.gov/wp-json/wp/v2/pages/9347",
    "process": {
      "source_code": "https://github.com/cagov/wordpress-to-github",
      "source_data": "https://api.cannabis.ca.gov",
      "deployment_target": "https://github.com/cagov/static-content-cannabis/tree/staging"
    },
    "refresh_frequency": "as needed"
  },
  "data": {
    "id": 9347,
    "date": "2022-01-26T08:55:22",
    "date_gmt": "2022-01-26T16:55:22",
    "guid": "https://cannabis.ca.gov/?page_id=9347",
    "modified": "2025-10-14T15:09:31",
    "modified_gmt": "2025-10-14T22:09:31",
    "slug": "mandatory-recall-2022-01-26",
    "status": "publish",
    "type": "page",
    "link": "https://api.cannabis.ca.gov/resources/cannabis-recalls-and-safety-notices/mandatory-recall-2022-01-26/",
    "title": "Mandatory recall: January 26, 2022",
    "excerpt": "<p>The&nbsp;Department of Cannabis Control (DCC) issued a mandatory recall&nbsp;on January 26, 2022,&nbsp;for&nbsp;one batch&nbsp;of cannabis flower contaminated with&nbsp;Aspergillus&nbsp;niger.&nbsp;&nbsp; Affected product&nbsp;information:&nbsp;&nbsp; What consumers need to know&nbsp; If you purchased Claybourne Co. Head Banger flower during the affected timeframe:&nbsp;&nbsp; According to the&nbsp;Centers for Disease Control and Prevention (CDC), most people breathe in Aspergillus spores every day without getting sick; [&hellip;]</p>\n",
    "author": 2,
    "featured_media": 0,
    "parent": 9345,
    "menu_order": 0,
    "comment_status": "closed",
    "ping_status": "closed",
    "template": "/code/wp-content/plugins/ca-design-system-gutenberg-blocks/includes/templates/template-page.php",
    "meta": {
      "_stopmodifiedupdate": false,
      "_modified_date": "",
      "footnotes": ""
    },
    "categories": [
      "Recalls and safety notices"
    ],
    "tags": [
      "new"
    ],
    "design_system_fields": {
      "template": "template-page"
    },
    "og_meta": {
      "editor": {
        "platform": "WordPress",
        "plugin": "autodescription",
        "plugin_name": "The SEO Framework",
        "plugin_version": "4.1.5.1",
        "editor_url": "https://api.cannabis.ca.gov"
      },
      "site_name": "Department of Cannabis Control",
      "site_description": "Learn about California cannabis laws and licenses",
      "site_url": "https://api.cannabis.ca.gov",
      "canonical_url": "https://api.cannabis.ca.gov/resources/cannabis-recalls-and-safety-notices/mandatory-recall-2022-01-26/",
      "page_title": "Mandatory recall: January 26, 2022",
      "page_description": "Learn about California cannabis laws and licenses",
      "page_social_image_url": "https://api.cannabis.ca.gov/wp-content/uploads/2021/07/cropped-Cannabis_horizontal_social.png",
      "page_social_image_width": 1200,
      "page_social_image_height": 630,
      "page_social_image_alt": "",
      "meta_title": "Mandatory recall: January 26, 2022",
      "meta_description": "Learn about California cannabis laws and licenses",
      "meta_canonical_url": "https://api.cannabis.ca.gov/resources/cannabis-recalls-and-safety-notices/mandatory-recall-2022-01-26/",
      "open_graph_title": "Mandatory recall: January 26, 2022",
      "open_graph_description": "Learn about California cannabis laws and licenses",
      "twitter_title": "Mandatory recall: January 26, 2022",
      "twitter_description": "Learn about California cannabis laws and licenses"
    },
    "headless_categories": [
      {
        "term_id": 812,
        "name": "Recalls and safety notices",
        "slug": "recalls-and-safety-notices",
        "term_group": 0,
        "term_taxonomy_id": 812,
        "taxonomy": "category",
        "description": "",
        "parent": 0,
        "filter": "raw",
        "cat_ID": 812,
        "category_description": "",
        "cat_name": "Recalls and safety notices",
        "category_nicename": "recalls-and-safety-notices",
        "category_parent": 0
      }
    ],
    "headless_tags": [
      {
        "term_id": 1017,
        "name": "new",
        "slug": "new",
        "term_group": 0,
        "term_taxonomy_id": 1017,
        "taxonomy": "post_tag",
        "description": "",
        "parent": 0,
        "filter": "raw"
      }
    ],
    "headless_publishing": [],
    "headless_preview": [],
    "wordpress_url": "https://api.cannabis.ca.gov/resources/cannabis-recalls-and-safety-notices/mandatory-recall-2022-01-26/"
  }
}